constraintoptimizer/__init__.py
constraintoptimizer/constraintoptimizer.py
lhztools-0.1.dist-info/METADATA
lhztools-0.1.dist-info/WHEEL
lhztools-0.1.dist-info/top_level.txt
lhztools-0.1.dist-info/RECORD
