Metadata-Version: 2.1
Name: lhztools
Version: 0.1
Summary: Tools for LHZ
Home-page: https://github.com/WolfgangLechner/lhztools
Author: Wolfgang Lechner
Author-email: wolfgang.lechner@gmail.com
License: MIT
Platform: UNKNOWN
